[
    {
        "total_awards_received": 0,
        "approved_at_utc": null,
        "comment_type": null,
        "awarders": [],
        "mod_reason_by": null,
        "banned_by": null,
        "author_flair_type": "richtext",
        "removal_reason": null,
        "link_id": "t3_gt0sdw",
        "author_flair_template_id": null,
        "likes": null,
        "replies": "",
        "user_reports": [],
        "saved": false,
        "id": "fs9x50a",
        "banned_at_utc": null,
        "mod_reason_title": null,
        "gilded": 0,
        "archived": true,
        "no_follow": false,
        "author": "PMBreakingNews",
        "num_comments": 21,
        "edited": false,
        "can_mod_post": false,
        "created_utc": 1590812138.0,
        "send_replies": true,
        "parent_id": "t1_fs9vjrj",
        "score": 3,
        "author_fullname": "t2_2ur0y6ik",
        "over_18": false,
        "treatment_tags": [],
        "approved_by": null,
        "mod_note": null,
        "all_awardings": [],
        "subreddit_id": "t5_2qzb6",
        "body": "We have three people that work on the team consistently and have access to the account. Dozens of people help us with news tips and we have some private Whatsapp groups we run with people posting news stories.\n\nWe don't make any money off the account- but have some closely-related side projects once in a while which helps us make a few thousand dollars a year. We've had a ton of advertisement opportunities (mostly news apps/sites), but don't bother with them because they can jeopardize our reputation and hurt the future growth of the account. \n\nThe truth is, Twitter really is the worst place to monetize. There are opportunities, but YouTube and Facebook would be better options if that is your primary goal. If you're not willing to spam your timeline or put in the time to create a website - it's going to be very difficult to make enough to do it full time.",
        "link_title": "We Are The Founders of a Breaking News Account with Over 210,000 Followers on Twitter. AMA.",
        "author_flair_css_class": null,
        "name": "t1_fs9x50a",
        "author_patreon_flair": false,
        "downs": 0,
        "author_flair_richtext": [
            {
                "a": ":verified:",
                "e": "emoji",
                "u": "https://emoji.redditmedia.com/c084y0ue7wv31_t5_2qzb6/verified"
            },
            {
                "e": "text",
                "t": " Verified"
            }
        ],
        "is_submitter": true,
        "body_html": "&lt;div class=\"md\"&gt;&lt;p&gt;We have three people that work on the team consistently and have access to the account. Dozens of people help us with news tips and we have some private Whatsapp groups we run with people posting news stories.&lt;/p&gt;\n\n&lt;p&gt;We don&amp;#39;t make any money off the account- but have some closely-related side projects once in a while which helps us make a few thousand dollars a year. We&amp;#39;ve had a ton of advertisement opportunities (mostly news apps/sites), but don&amp;#39;t bother with them because they can jeopardize our reputation and hurt the future growth of the account. &lt;/p&gt;\n\n&lt;p&gt;The truth is, Twitter really is the worst place to monetize. There are opportunities, but YouTube and Facebook would be better options if that is your primary goal. If you&amp;#39;re not willing to spam your timeline or put in the time to create a website - it&amp;#39;s going to be very difficult to make enough to do it full time.&lt;/p&gt;\n&lt;/div&gt;",
        "gildings": {},
        "collapsed_reason": null,
        "distinguished": null,
        "associated_award": null,
        "stickied": false,
        "author_premium": false,
        "can_gild": true,
        "top_awarded_type": null,
        "author_flair_text_color": "dark",
        "score_hidden": false,
        "permalink": "/r/IAmA/comments/gt0sdw/we_are_the_founders_of_a_breaking_news_account/fs9x50a/",
        "num_reports": null,
        "link_permalink": "https://www.reddit.com/r/IAmA/comments/gt0sdw/we_are_the_founders_of_a_breaking_news_account/",
        "report_reasons": null,
        "link_author": "PMBreakingNews",
        "subreddit": "IAmA",
        "author_flair_text": ":verified: Verified",
        "link_url": "https://www.reddit.com/r/IAmA/comments/gt0sdw/we_are_the_founders_of_a_breaking_news_account/",
        "created": 1590840938.0,
        "collapsed": false,
        "subreddit_name_prefixed": "r/IAmA",
        "controversiality": 0,
        "locked": false,
        "author_flair_background_color": "",
        "collapsed_because_crowd_control": null,
        "mod_reports": [],
        "quarantine": false,
        "subreddit_type": "public",
        "ups": 3
    },
    {
        "total_awards_received": 0,
        "approved_at_utc": null,
        "comment_type": null,
        "awarders": [],
        "mod_reason_by": null,
        "banned_by": null,
        "author_flair_type": "richtext",
        "removal_reason": null,
        "link_id": "t3_gt0sdw",
        "author_flair_template_id": null,
        "likes": null,
        "replies": "",
        "user_reports": [],
        "saved": false,
        "id": "fs9ff60",
        "banned_at_utc": null,
        "mod_reason_title": null,
        "gilded": 0,
        "archived": true,
        "no_follow": false,
        "author": "PMBreakingNews",
        "num_comments": 21,
        "edited": false,
        "can_mod_post": false,
        "created_utc": 1590800944.0,
        "send_replies": true,
        "parent_id": "t1_fs9988f",
        "score": 2,
        "author_fullname": "t2_2ur0y6ik",
        "over_18": false,
        "treatment_tags": [],
        "approved_by": null,
        "mod_note": null,
        "all_awardings": [],
        "subreddit_id": "t5_2qzb6",
        "body": "We have a pretty large following base, which makes it easy for us to limit the time it takes to pick up on a story. Additionally, we have some private news communities we run on WhatsApp, where news enthusiasts often help notify us about developing events. All the people directly involved in the account are personal friends so that keeps communications steady. \n\nOverall, I would say that because of the system we have in place, it really isn't time-consuming and hence is easy to sustain. The only thing that takes up a lot of time is really ongoing events, such as the riots we've been seeing over the past few nights. Also, even though there's pressure for us to keep up with everything - everyone on our team still views it as an enjoyable hobby rather than a job.",
        "link_title": "We Are The Founders of a Breaking News Account with Over 210,000 Followers on Twitter. AMA.",
        "author_flair_css_class": null,
        "name": "t1_fs9ff60",
        "author_patreon_flair": false,
        "downs": 0,
        "author_flair_richtext": [
            {
                "a": ":verified:",
                "e": "emoji",
                "u": "https://emoji.redditmedia.com/c084y0ue7wv31_t5_2qzb6/verified"
            },
            {
                "e": "text",
                "t": " Verified"
            }
        ],
        "is_submitter": true,
        "body_html": "&lt;div class=\"md\"&gt;&lt;p&gt;We have a pretty large following base, which makes it easy for us to limit the time it takes to pick up on a story. Additionally, we have some private news communities we run on WhatsApp, where news enthusiasts often help notify us about developing events. All the people directly involved in the account are personal friends so that keeps communications steady. &lt;/p&gt;\n\n&lt;p&gt;Overall, I would say that because of the system we have in place, it really isn&amp;#39;t time-consuming and hence is easy to sustain. The only thing that takes up a lot of time is really ongoing events, such as the riots we&amp;#39;ve been seeing over the past few nights. Also, even though there&amp;#39;s pressure for us to keep up with everything - everyone on our team still views it as an enjoyable hobby rather than a job.&lt;/p&gt;\n&lt;/div&gt;",
        "gildings": {},
        "collapsed_reason": null,
        "distinguished": null,
        "associated_award": null,
        "stickied": false,
        "author_premium": false,
        "can_gild": true,
        "top_awarded_type": null,
        "author_flair_text_color": "dark",
        "score_hidden": false,
        "permalink": "/r/IAmA/comments/gt0sdw/we_are_the_founders_of_a_breaking_news_account/fs9ff60/",
        "num_reports": null,
        "link_permalink": "https://www.reddit.com/r/IAmA/comments/gt0sdw/we_are_the_founders_of_a_breaking_news_account/",
        "report_reasons": null,
        "link_author": "PMBreakingNews",
        "subreddit": "IAmA",
        "author_flair_text": ":verified: Verified",
        "link_url": "https://www.reddit.com/r/IAmA/comments/gt0sdw/we_are_the_founders_of_a_breaking_news_account/",
        "created": 1590829744.0,
        "collapsed": false,
        "subreddit_name_prefixed": "r/IAmA",
        "controversiality": 0,
        "locked": false,
        "author_flair_background_color": "",
        "collapsed_because_crowd_control": null,
        "mod_reports": [],
        "quarantine": false,
        "subreddit_type": "public",
        "ups": 2
    },
    {
        "total_awards_received": 0,
        "approved_at_utc": null,
        "comment_type": null,
        "awarders": [],
        "mod_reason_by": null,
        "banned_by": null,
        "author_flair_type": "richtext",
        "removal_reason": null,
        "link_id": "t3_gt0sdw",
        "author_flair_template_id": null,
        "likes": null,
        "replies": "",
        "user_reports": [],
        "saved": false,
        "id": "fs8xo9h",
        "banned_at_utc": null,
        "mod_reason_title": null,
        "gilded": 0,
        "archived": true,
        "no_follow": false,
        "author": "PMBreakingNews",
        "num_comments": 21,
        "edited": false,
        "can_mod_post": false,
        "created_utc": 1590790876.0,
        "send_replies": true,
        "parent_id": "t1_fs8x603",
        "score": 1,
        "author_fullname": "t2_2ur0y6ik",
        "over_18": false,
        "treatment_tags": [],
        "approved_by": null,
        "mod_note": null,
        "all_awardings": [],
        "subreddit_id": "t5_2qzb6",
        "body": "We do usually look for specific kinds of events - like natural disasters, conflicts, or terrorism. \n\nWe are probably more likely to cover a large building fire in the U.S. than other countries (especially countries where it's a common occurrence). \n\nUsually if we'd cover events in lesser-known areas, they'd be related to earthquakes or storms.",
        "link_title": "We Are The Founders of a Breaking News Account with Over 210,000 Followers on Twitter. AMA.",
        "author_flair_css_class": null,
        "name": "t1_fs8xo9h",
        "author_patreon_flair": false,
        "downs": 0,
        "author_flair_richtext": [
            {
                "a": ":verified:",
                "e": "emoji",
                "u": "https://emoji.redditmedia.com/c084y0ue7wv31_t5_2qzb6/verified"
            },
            {
                "e": "text",
                "t": " Verified"
            }
        ],
        "is_submitter": true,
        "body_html": "&lt;div class=\"md\"&gt;&lt;p&gt;We do usually look for specific kinds of events - like natural disasters, conflicts, or terrorism. &lt;/p&gt;\n\n&lt;p&gt;We are probably more likely to cover a large building fire in the U.S. than other countries (especially countries where it&amp;#39;s a common occurrence). &lt;/p&gt;\n\n&lt;p&gt;Usually if we&amp;#39;d cover events in lesser-known areas, they&amp;#39;d be related to earthquakes or storms.&lt;/p&gt;\n&lt;/div&gt;",
        "gildings": {},
        "collapsed_reason": null,
        "distinguished": null,
        "associated_award": null,
        "stickied": false,
        "author_premium": false,
        "can_gild": true,
        "top_awarded_type": null,
        "author_flair_text_color": "dark",
        "score_hidden": false,
        "permalink": "/r/IAmA/comments/gt0sdw/we_are_the_founders_of_a_breaking_news_account/fs8xo9h/",
        "num_reports": null,
        "link_permalink": "https://www.reddit.com/r/IAmA/comments/gt0sdw/we_are_the_founders_of_a_breaking_news_account/",
        "report_reasons": null,
        "link_author": "PMBreakingNews",
        "subreddit": "IAmA",
        "author_flair_text": ":verified: Verified",
        "link_url": "https://www.reddit.com/r/IAmA/comments/gt0sdw/we_are_the_founders_of_a_breaking_news_account/",
        "created": 1590819676.0,
        "collapsed": false,
        "subreddit_name_prefixed": "r/IAmA",
        "controversiality": 0,
        "locked": false,
        "author_flair_background_color": "",
        "collapsed_because_crowd_control": null,
        "mod_reports": [],
        "quarantine": false,
        "subreddit_type": "public",
        "ups": 1
    },
    {
        "total_awards_received": 0,
        "approved_at_utc": null,
        "comment_type": null,
        "awarders": [],
        "mod_reason_by": null,
        "banned_by": null,
        "author_flair_type": "richtext",
        "removal_reason": null,
        "link_id": "t3_gt0sdw",
        "author_flair_template_id": null,
        "likes": null,
        "replies": "",
        "user_reports": [],
        "saved": false,
        "id": "fs8wwid",
        "banned_at_utc": null,
        "mod_reason_title": null,
        "gilded": 0,
        "archived": true,
        "no_follow": false,
        "author": "PMBreakingNews",
        "num_comments": 21,
        "edited": false,
        "can_mod_post": false,
        "created_utc": 1590790462.0,
        "send_replies": true,
        "parent_id": "t1_fs8vg8d",
        "score": 2,
        "author_fullname": "t2_2ur0y6ik",
        "over_18": false,
        "treatment_tags": [],
        "approved_by": null,
        "mod_note": null,
        "all_awardings": [],
        "subreddit_id": "t5_2qzb6",
        "body": "I wouldn't say we cover a lot of weird news- but we definitely get a lot of strange tips. \n\nI remember early last year someone sent us a news story about a man dating a cockroach and when the cockroach died, the man ate it. We all got a kick out of it and thought it was fake but it turned out to be real. We didn't end up covering it because it wasn't really breaking news (and I'm not sure why someone would think it is lol), but it was definitely the most bizarre story I've encountered.",
        "link_title": "We Are The Founders of a Breaking News Account with Over 210,000 Followers on Twitter. AMA.",
        "author_flair_css_class": null,
        "name": "t1_fs8wwid",
        "author_patreon_flair": false,
        "downs": 0,
        "author_flair_richtext": [
            {
                "a": ":verified:",
                "e": "emoji",
                "u": "https://emoji.redditmedia.com/c084y0ue7wv31_t5_2qzb6/verified"
            },
            {
                "e": "text",
                "t": " Verified"
            }
        ],
        "is_submitter": true,
        "body_html": "&lt;div class=\"md\"&gt;&lt;p&gt;I wouldn&amp;#39;t say we cover a lot of weird news- but we definitely get a lot of strange tips. &lt;/p&gt;\n\n&lt;p&gt;I remember early last year someone sent us a news story about a man dating a cockroach and when the cockroach died, the man ate it. We all got a kick out of it and thought it was fake but it turned out to be real. We didn&amp;#39;t end up covering it because it wasn&amp;#39;t really breaking news (and I&amp;#39;m not sure why someone would think it is lol), but it was definitely the most bizarre story I&amp;#39;ve encountered.&lt;/p&gt;\n&lt;/div&gt;",
        "gildings": {},
        "collapsed_reason": null,
        "distinguished": null,
        "associated_award": null,
        "stickied": false,
        "author_premium": false,
        "can_gild": true,
        "top_awarded_type": null,
        "author_flair_text_color": "dark",
        "score_hidden": false,
        "permalink": "/r/IAmA/comments/gt0sdw/we_are_the_founders_of_a_breaking_news_account/fs8wwid/",
        "num_reports": null,
        "link_permalink": "https://www.reddit.com/r/IAmA/comments/gt0sdw/we_are_the_founders_of_a_breaking_news_account/",
        "report_reasons": null,
        "link_author": "PMBreakingNews",
        "subreddit": "IAmA",
        "author_flair_text": ":verified: Verified",
        "link_url": "https://www.reddit.com/r/IAmA/comments/gt0sdw/we_are_the_founders_of_a_breaking_news_account/",
        "created": 1590819262.0,
        "collapsed": false,
        "subreddit_name_prefixed": "r/IAmA",
        "controversiality": 0,
        "locked": false,
        "author_flair_background_color": "",
        "collapsed_because_crowd_control": null,
        "mod_reports": [],
        "quarantine": false,
        "subreddit_type": "public",
        "ups": 2
    },
    {
        "total_awards_received": 0,
        "approved_at_utc": null,
        "comment_type": null,
        "awarders": [],
        "mod_reason_by": null,
        "banned_by": null,
        "author_flair_type": "richtext",
        "removal_reason": null,
        "link_id": "t3_gt0sdw",
        "author_flair_template_id": null,
        "likes": null,
        "replies": "",
        "user_reports": [],
        "saved": false,
        "id": "fs8vmyf",
        "banned_at_utc": null,
        "mod_reason_title": null,
        "gilded": 0,
        "archived": true,
        "no_follow": false,
        "author": "PMBreakingNews",
        "num_comments": 21,
        "edited": false,
        "can_mod_post": false,
        "created_utc": 1590789800.0,
        "send_replies": true,
        "parent_id": "t1_fs8v0kf",
        "score": 1,
        "author_fullname": "t2_2ur0y6ik",
        "over_18": false,
        "treatment_tags": [],
        "approved_by": null,
        "mod_note": null,
        "all_awardings": [],
        "subreddit_id": "t5_2qzb6",
        "body": "Most of our base is from the U.S., so most of the news tips we get are domestic. However, we try to do our best to cover news stories internationally. Over the past year, we've tried to increase our presence in other countries and build relationships with people on the ground there.",
        "link_title": "We Are The Founders of a Breaking News Account with Over 210,000 Followers on Twitter. AMA.",
        "author_flair_css_class": null,
        "name": "t1_fs8vmyf",
        "author_patreon_flair": false,
        "downs": 0,
        "author_flair_richtext": [
            {
                "a": ":verified:",
                "e": "emoji",
                "u": "https://emoji.redditmedia.com/c084y0ue7wv31_t5_2qzb6/verified"
            },
            {
                "e": "text",
                "t": " Verified"
            }
        ],
        "is_submitter": true,
        "body_html": "&lt;div class=\"md\"&gt;&lt;p&gt;Most of our base is from the U.S., so most of the news tips we get are domestic. However, we try to do our best to cover news stories internationally. Over the past year, we&amp;#39;ve tried to increase our presence in other countries and build relationships with people on the ground there.&lt;/p&gt;\n&lt;/div&gt;",
        "gildings": {},
        "collapsed_reason": null,
        "distinguished": null,
        "associated_award": null,
        "stickied": false,
        "author_premium": false,
        "can_gild": true,
        "top_awarded_type": null,
        "author_flair_text_color": "dark",
        "score_hidden": false,
        "permalink": "/r/IAmA/comments/gt0sdw/we_are_the_founders_of_a_breaking_news_account/fs8vmyf/",
        "num_reports": null,
        "link_permalink": "https://www.reddit.com/r/IAmA/comments/gt0sdw/we_are_the_founders_of_a_breaking_news_account/",
        "report_reasons": null,
        "link_author": "PMBreakingNews",
        "subreddit": "IAmA",
        "author_flair_text": ":verified: Verified",
        "link_url": "https://www.reddit.com/r/IAmA/comments/gt0sdw/we_are_the_founders_of_a_breaking_news_account/",
        "created": 1590818600.0,
        "collapsed": false,
        "subreddit_name_prefixed": "r/IAmA",
        "controversiality": 0,
        "locked": false,
        "author_flair_background_color": "",
        "collapsed_because_crowd_control": null,
        "mod_reports": [],
        "quarantine": false,
        "subreddit_type": "public",
        "ups": 1
    },
    {
        "total_awards_received": 0,
        "approved_at_utc": null,
        "comment_type": null,
        "awarders": [],
        "mod_reason_by": null,
        "banned_by": null,
        "author_flair_type": "richtext",
        "removal_reason": null,
        "link_id": "t3_gt0sdw",
        "author_flair_template_id": null,
        "likes": null,
        "replies": "",
        "user_reports": [],
        "saved": false,
        "id": "fs8rug9",
        "banned_at_utc": null,
        "mod_reason_title": null,
        "gilded": 0,
        "archived": true,
        "no_follow": false,
        "author": "PMBreakingNews",
        "num_comments": 21,
        "edited": 1590793259.0,
        "can_mod_post": false,
        "created_utc": 1590787851.0,
        "send_replies": true,
        "parent_id": "t1_fs8lm6i",
        "score": 1,
        "author_fullname": "t2_2ur0y6ik",
        "over_18": false,
        "treatment_tags": [],
        "approved_by": null,
        "mod_note": null,
        "all_awardings": [],
        "subreddit_id": "t5_2qzb6",
        "body": "Early on we sometimes posted specifics such as death numbers from verified news sources that later turned out to be inaccurate, since then we make sure to get our news from a variety of reliable sources before posting.\n\nEdit: Another regretful post- Once we received a tip on a video from a scene of a shooting and we posted it. A lot of people ended up complaining that we may be giving away police positions and we deleted the video. Since then we make sure to avoid posting any police positions that can jeopardize any operations. \n\nA lot of things you don't think will be a problem to post- but you find out it is along the way. That's why it's so important to consider and take any feedback you can get (Even if negative).",
        "link_title": "We Are The Founders of a Breaking News Account with Over 210,000 Followers on Twitter. AMA.",
        "author_flair_css_class": null,
        "name": "t1_fs8rug9",
        "author_patreon_flair": false,
        "downs": 0,
        "author_flair_richtext": [
            {
                "a": ":verified:",
                "e": "emoji",
                "u": "https://emoji.redditmedia.com/c084y0ue7wv31_t5_2qzb6/verified"
            },
            {
                "e": "text",
                "t": " Verified"
            }
        ],
        "is_submitter": true,
        "body_html": "&lt;div class=\"md\"&gt;&lt;p&gt;Early on we sometimes posted specifics such as death numbers from verified news sources that later turned out to be inaccurate, since then we make sure to get our news from a variety of reliable sources before posting.&lt;/p&gt;\n\n&lt;p&gt;Edit: Another regretful post- Once we received a tip on a video from a scene of a shooting and we posted it. A lot of people ended up complaining that we may be giving away police positions and we deleted the video. Since then we make sure to avoid posting any police positions that can jeopardize any operations. &lt;/p&gt;\n\n&lt;p&gt;A lot of things you don&amp;#39;t think will be a problem to post- but you find out it is along the way. That&amp;#39;s why it&amp;#39;s so important to consider and take any feedback you can get (Even if negative).&lt;/p&gt;\n&lt;/div&gt;",
        "gildings": {},
        "collapsed_reason": null,
        "distinguished": null,
        "associated_award": null,
        "stickied": false,
        "author_premium": false,
        "can_gild": true,
        "top_awarded_type": null,
        "author_flair_text_color": "dark",
        "score_hidden": false,
        "permalink": "/r/IAmA/comments/gt0sdw/we_are_the_founders_of_a_breaking_news_account/fs8rug9/",
        "num_reports": null,
        "link_permalink": "https://www.reddit.com/r/IAmA/comments/gt0sdw/we_are_the_founders_of_a_breaking_news_account/",
        "report_reasons": null,
        "link_author": "PMBreakingNews",
        "subreddit": "IAmA",
        "author_flair_text": ":verified: Verified",
        "link_url": "https://www.reddit.com/r/IAmA/comments/gt0sdw/we_are_the_founders_of_a_breaking_news_account/",
        "created": 1590816651.0,
        "collapsed": false,
        "subreddit_name_prefixed": "r/IAmA",
        "controversiality": 0,
        "locked": false,
        "author_flair_background_color": "",
        "collapsed_because_crowd_control": null,
        "mod_reports": [],
        "quarantine": false,
        "subreddit_type": "public",
        "ups": 1
    },
    {
        "total_awards_received": 0,
        "approved_at_utc": null,
        "comment_type": null,
        "awarders": [],
        "mod_reason_by": null,
        "banned_by": null,
        "author_flair_type": "richtext",
        "removal_reason": null,
        "link_id": "t3_gt0sdw",
        "author_flair_template_id": null,
        "likes": null,
        "replies": "",
        "user_reports": [],
        "saved": false,
        "id": "fs8ra7e",
        "banned_at_utc": null,
        "mod_reason_title": null,
        "gilded": 0,
        "archived": true,
        "no_follow": false,
        "author": "PMBreakingNews",
        "num_comments": 21,
        "edited": false,
        "can_mod_post": false,
        "created_utc": 1590787563.0,
        "send_replies": true,
        "parent_id": "t1_fs8lj9i",
        "score": 3,
        "author_fullname": "t2_2ur0y6ik",
        "over_18": false,
        "treatment_tags": [],
        "approved_by": null,
        "mod_note": null,
        "all_awardings": [],
        "subreddit_id": "t5_2qzb6",
        "body": "The hardest story we covered was probably the Iran conflict in December/January. The entire conflict happened very fast and there was a lot of conflicting information between what the domestic media was sharing and what was being shared on the ground. \n\nUsually, when any news event occurs there are conflicting numbers (of injuries/deaths/damage) or locations. In these cases, we usually wouldn’t specify these details before verified by government sources, but would still get the basics of the story before most mainstream sources. \n\nHowever, during the Iran story, major events that could’ve created long term conflict in the region were being disputed and stakes were much higher for our credibility.",
        "link_title": "We Are The Founders of a Breaking News Account with Over 210,000 Followers on Twitter. AMA.",
        "author_flair_css_class": null,
        "name": "t1_fs8ra7e",
        "author_patreon_flair": false,
        "downs": 0,
        "author_flair_richtext": [
            {
                "a": ":verified:",
                "e": "emoji",
                "u": "https://emoji.redditmedia.com/c084y0ue7wv31_t5_2qzb6/verified"
            },
            {
                "e": "text",
                "t": " Verified"
            }
        ],
        "is_submitter": true,
        "body_html": "&lt;div class=\"md\"&gt;&lt;p&gt;The hardest story we covered was probably the Iran conflict in December/January. The entire conflict happened very fast and there was a lot of conflicting information between what the domestic media was sharing and what was being shared on the ground. &lt;/p&gt;\n\n&lt;p&gt;Usually, when any news event occurs there are conflicting numbers (of injuries/deaths/damage) or locations. In these cases, we usually wouldn’t specify these details before verified by government sources, but would still get the basics of the story before most mainstream sources. &lt;/p&gt;\n\n&lt;p&gt;However, during the Iran story, major events that could’ve created long term conflict in the region were being disputed and stakes were much higher for our credibility.&lt;/p&gt;\n&lt;/div&gt;",
        "gildings": {},
        "collapsed_reason": null,
        "distinguished": null,
        "associated_award": null,
        "stickied": false,
        "author_premium": false,
        "can_gild": true,
        "top_awarded_type": null,
        "author_flair_text_color": "dark",
        "score_hidden": false,
        "permalink": "/r/IAmA/comments/gt0sdw/we_are_the_founders_of_a_breaking_news_account/fs8ra7e/",
        "num_reports": null,
        "link_permalink": "https://www.reddit.com/r/IAmA/comments/gt0sdw/we_are_the_founders_of_a_breaking_news_account/",
        "report_reasons": null,
        "link_author": "PMBreakingNews",
        "subreddit": "IAmA",
        "author_flair_text": ":verified: Verified",
        "link_url": "https://www.reddit.com/r/IAmA/comments/gt0sdw/we_are_the_founders_of_a_breaking_news_account/",
        "created": 1590816363.0,
        "collapsed": false,
        "subreddit_name_prefixed": "r/IAmA",
        "controversiality": 0,
        "locked": false,
        "author_flair_background_color": "",
        "collapsed_because_crowd_control": null,
        "mod_reports": [],
        "quarantine": false,
        "subreddit_type": "public",
        "ups": 3
    },
    {
        "total_awards_received": 0,
        "approved_at_utc": null,
        "comment_type": null,
        "awarders": [],
        "mod_reason_by": null,
        "banned_by": null,
        "author_flair_type": "text",
        "removal_reason": null,
        "link_id": "t3_cir8si",
        "author_flair_template_id": null,
        "likes": null,
        "replies": "",
        "user_reports": [],
        "saved": false,
        "id": "ev8qq46",
        "banned_at_utc": null,
        "mod_reason_title": null,
        "gilded": 0,
        "archived": true,
        "no_follow": false,
        "author": "PMBreakingNews",
        "num_comments": 15,
        "edited": false,
        "can_mod_post": false,
        "created_utc": 1564288110.0,
        "send_replies": true,
        "parent_id": "t3_cir8si",
        "score": 15,
        "author_fullname": "t2_2ur0y6ik",
        "over_18": false,
        "treatment_tags": [],
        "approved_by": null,
        "mod_note": null,
        "all_awardings": [],
        "subreddit_id": "t5_2qme3",
        "body": "12 now reportedly shot. At least one dead.",
        "link_title": "Six Injured After Shooting in a Playground in Brownsville",
        "author_flair_css_class": null,
        "name": "t1_ev8qq46",
        "author_patreon_flair": false,
        "downs": 0,
        "author_flair_richtext": [],
        "is_submitter": true,
        "body_html": "&lt;div class=\"md\"&gt;&lt;p&gt;12 now reportedly shot. At least one dead.&lt;/p&gt;\n&lt;/div&gt;",
        "gildings": {},
        "collapsed_reason": null,
        "distinguished": null,
        "associated_award": null,
        "stickied": false,
        "author_premium": false,
        "can_gild": true,
        "top_awarded_type": null,
        "author_flair_text_color": null,
        "score_hidden": false,
        "permalink": "/r/Brooklyn/comments/cir8si/six_injured_after_shooting_in_a_playground_in/ev8qq46/",
        "num_reports": null,
        "link_permalink": "https://www.reddit.com/r/Brooklyn/comments/cir8si/six_injured_after_shooting_in_a_playground_in/",
        "report_reasons": null,
        "link_author": "PMBreakingNews",
        "subreddit": "Brooklyn",
        "author_flair_text": null,
        "link_url": "https://portermedium.com/2019/07/multiple-shot-in-a-park-in-brooklyn-new-york/",
        "created": 1564316910.0,
        "collapsed": false,
        "subreddit_name_prefixed": "r/Brooklyn",
        "controversiality": 0,
        "locked": false,
        "author_flair_background_color": null,
        "collapsed_because_crowd_control": null,
        "mod_reports": [],
        "quarantine": false,
        "subreddit_type": "public",
        "ups": 15
    },
    {
        "total_awards_received": 0,
        "approved_at_utc": null,
        "comment_type": null,
        "awarders": [],
        "mod_reason_by": null,
        "banned_by": null,
        "author_flair_type": "text",
        "removal_reason": null,
        "link_id": "t3_b4ly2h",
        "author_flair_template_id": null,
        "likes": null,
        "replies": "",
        "user_reports": [],
        "saved": false,
        "id": "ej84hrg",
        "banned_at_utc": null,
        "mod_reason_title": null,
        "gilded": 0,
        "archived": true,
        "no_follow": true,
        "author": "PMBreakingNews",
        "num_comments": 20,
        "edited": false,
        "can_mod_post": false,
        "created_utc": 1553378064.0,
        "send_replies": true,
        "parent_id": "t3_b4ly2h",
        "score": 1,
        "author_fullname": "t2_2ur0y6ik",
        "over_18": false,
        "treatment_tags": [],
        "approved_by": null,
        "mod_note": null,
        "all_awardings": [],
        "subreddit_id": "t5_2qhwg",
        "body": "Hi, I am trying to spread awareness as well. I tweeted out about it and got 41 retweets so far, hoping to gain some stream.\n\n&amp;#x200B;\n\nhttps://twitter.com/JeffreyPorterPM/status/1109569619067654146",
        "link_title": "Twitters Never Ending Resetting Loop Can Affect You Next!",
        "author_flair_css_class": null,
        "name": "t1_ej84hrg",
        "author_patreon_flair": false,
        "downs": 0,
        "author_flair_richtext": [],
        "is_submitter": false,
        "body_html": "&lt;div class=\"md\"&gt;&lt;p&gt;Hi, I am trying to spread awareness as well. I tweeted out about it and got 41 retweets so far, hoping to gain some stream.&lt;/p&gt;\n\n&lt;p&gt;&amp;#x200B;&lt;/p&gt;\n\n&lt;p&gt;&lt;a href=\"https://twitter.com/JeffreyPorterPM/status/1109569619067654146\"&gt;https://twitter.com/JeffreyPorterPM/status/1109569619067654146&lt;/a&gt;&lt;/p&gt;\n&lt;/div&gt;",
        "gildings": {},
        "collapsed_reason": null,
        "distinguished": null,
        "associated_award": null,
        "stickied": false,
        "author_premium": false,
        "can_gild": true,
        "top_awarded_type": null,
        "author_flair_text_color": null,
        "score_hidden": false,
        "permalink": "/r/Twitter/comments/b4ly2h/twitters_never_ending_resetting_loop_can_affect/ej84hrg/",
        "num_reports": null,
        "link_permalink": "https://www.reddit.com/r/Twitter/comments/b4ly2h/twitters_never_ending_resetting_loop_can_affect/",
        "report_reasons": null,
        "link_author": "[deleted]",
        "subreddit": "Twitter",
        "author_flair_text": null,
        "link_url": "https://link.medium.com/8lqWGjstiV",
        "created": 1553406864.0,
        "collapsed": false,
        "subreddit_name_prefixed": "r/Twitter",
        "controversiality": 0,
        "locked": false,
        "author_flair_background_color": null,
        "collapsed_because_crowd_control": null,
        "mod_reports": [],
        "quarantine": false,
        "subreddit_type": "public",
        "ups": 1
    }
]